zbrowser/__init__.py
zbrowser/chrome.py
zbrowser/utility.py
zbrowser-0.1.3.dist-info/METADATA
zbrowser-0.1.3.dist-info/WHEEL
zbrowser-0.1.3.dist-info/licenses/LICENSE
zbrowser-0.1.3.dist-info/RECORD
