Metadata-Version: 2.1
Name: zbrowser
Version: 0.1.3
Summary: zen browser library
Project-URL: Homepage, https://github.com/inspirare6/zbrowser
Project-URL: Bug Tracker, https://github.com/inspirare6/zbrowser/issues
Author-email: inspirare6 <inspirare6@163.com>
License-File: LICENSE
Classifier: License :: OSI Approved :: MIT License
Classifier: Operating System :: OS Independent
Classifier: Programming Language :: Python :: 3
Requires-Python: >=3.7
Requires-Dist: selenium-stealth==1.0.6
Requires-Dist: selenium==4.8.2
